plc_simulate/__init__.py
plc_simulate/app.py
plc_simulate/blueprints/__init__.py
plc_simulate/blueprints/index.py
plc_simulate/blueprints/plc_simulate.py
plc_simulate/static/img/favicon.ico
plc_simulate/static/layui/css/layui.css
plc_simulate/static/layui/font/iconfont.eot
plc_simulate/static/layui/font/iconfont.svg
plc_simulate/static/layui/font/iconfont.ttf
plc_simulate/static/layui/font/iconfont.woff
plc_simulate/static/layui/font/iconfont.woff2
plc_simulate/static/layui/layui.js
plc_simulate/static/layui_exts/translate/translate.js
plc_simulate/templates/cyg_base.html
plc_simulate/templates/cyg_plc_simulate.html
plc_simulate/templates/cyg_welcome.html
plc_simulate-0.1.0.dist-info/METADATA
plc_simulate-0.1.0.dist-info/WHEEL
plc_simulate-0.1.0.dist-info/RECORD
