Metadata-Version: 2.1
Name: plc_simulate
Version: 0.1.0
Summary: plc 模拟器
Author: LiuWei
Author-email: 183074632@qq.com
Requires-Python: >=3.8,<3.13
Classifier: Programming Language :: Python :: 3
Classifier: Programming Language :: Python :: 3.8
Classifier: Programming Language :: Python :: 3.9
Classifier: Programming Language :: Python :: 3.10
Classifier: Programming Language :: Python :: 3.11
Classifier: Programming Language :: Python :: 3.12
Requires-Dist: flask (>=3.0.3,<4.0.0)
Requires-Dist: inovance-tag-cyg (>=0.2.3,<0.3.0)
Requires-Dist: pythonnet (>=3.0.3,<4.0.0)
